cellstitch_cuda/__init__.py
cellstitch_cuda/alignment.py
cellstitch_cuda/evaluation.py
cellstitch_cuda/frame.py
cellstitch_cuda/interpolate.py
cellstitch_cuda/pipeline.py
cellstitch_cuda/postprocessing_cupy.py
cellstitch_cuda/preprocessing_cupy.py
cellstitch_cuda/seg_batch.py
cellstitch_cuda-1.5.4.dist-info/licenses/LICENSE
dev/main.py
dev/main_masks.py
cellstitch_cuda-1.5.4.dist-info/METADATA
cellstitch_cuda-1.5.4.dist-info/WHEEL
cellstitch_cuda-1.5.4.dist-info/top_level.txt
cellstitch_cuda-1.5.4.dist-info/RECORD
