Metadata-Version: 2.4
Name: cellstitch-cuda
Version: 1.5.4
Summary: CUDA-accelerated CellStitch 3D labeling using Instanseg segmentation.
Author-email: Tom van Leeuwen <tom@tleeuwen.nl>
Project-URL: Homepage, https://github.com/Tomvl117/cellstitch-cuda
Keywords: 3D labeling,cell labels,2D stitching
Classifier: Environment :: GPU :: NVIDIA CUDA :: 11
Classifier: Environment :: GPU :: NVIDIA CUDA :: 12
Classifier: License :: OSI Approved :: MIT License
Classifier: Programming Language :: Python :: 3
Classifier: Operating System :: Microsoft :: Windows
Classifier: Topic :: Scientific/Engineering :: Image Processing
Requires-Python: <3.12,>=3.9
License-File: LICENSE
Requires-Dist: instanseg-torch>=0.0.6
Requires-Dist: cellpose>=3.1.0
Requires-Dist: POT>=0.8.1
Requires-Dist: sphinx
Requires-Dist: sphinxcontrib-apidoc
Requires-Dist: tifffile
Requires-Dist: numpy<2.0.0
Requires-Dist: cupy-cuda12x
Requires-Dist: joblib
Requires-Dist: fill-voids
Dynamic: license-file
